business/__init__.py
business/bond/__init__.py
business/bond/bondinfo.py
business/english/__init__.py
business/english/english.py
business/fund/__init__.py
business/fund/fundinfo.py
business/futures/__init__.py
business/futures/futuresinfo.py
business/macro/__init__.py
business/macro/nationaleconomy.py
business/neeq/__init__.py
business/neeq/neeqinfo.py
business/news/__init__.py
business/oversea/__init__.py
business/oversea/oversea.py
business/public/__init__.py
business/public/industry.py
business/public/pubcode.py
business/stock/__init__.py
business/stock/announcement.py
business/stock/baseinfo.py
business/stock/hk.py
business/stock/index.py
business/stock/market.py
business/stock/news.py
business/stock/report.py
business/stock/tradedate.py
dataapi/__init__.py
dataapi/client.py
dataapi/datamart.py
dataapi/conf/__init__.py
dataapi/conf/apilog.py
dataapi/conf/clientinfo.py
dataapi/conf/requestparam.py
dataapi/conf/serverinfo.py
dataapi/conf/vars.py
dataapi/conf/webapiconf.py
dataapi/meta/__init__.py
dataapi/meta/apiinfo.py
dataapi/statistics/__init__.py
dataapi/statistics/apistatistics.py
test/__init__.py
test/apitest.py
util/__init__.py
util/auth.py
util/checkinputparam.py
util/datehelper.py
util/mapcolnames.py
cninfowebapi-0.1.4.dist-info/METADATA
cninfowebapi-0.1.4.dist-info/WHEEL
cninfowebapi-0.1.4.dist-info/top_level.txt
cninfowebapi-0.1.4.dist-info/RECORD
